slai/__init__.py
slai/base_handler.py
slai/clients/__init__.py
slai/clients/cli.py
slai/clients/identity.py
slai/clients/inference.py
slai/clients/model.py
slai/config.py
slai/constants.py
slai/exceptions.py
slai/login.py
slai/model.py
slai/modules/__init__.py
slai/modules/parameters.py
slai/modules/runtime.py
slai/types.py
slai-0.1.87.dist-info/WHEEL
slai-0.1.87.dist-info/METADATA
slai-0.1.87.dist-info/RECORD
